raiblocks_exporter
