Metadata-Version: 1.1
Name: raiblocks-exporter
Version: 0.0.3
Summary: Raiblocks Prometheus exporter
Home-page: https://github.com/ThunderOps/raiblocks-exporter
Author: Steven Acreman
Author-email: sacreman@gmail.com
License: Apache License, Version 2.0
Download-URL: https://github.com/ThunderOps/raiblocks-exporter
Keywords: Raiblocks Prometheus Exporter
Platform: any
Classifier: Intended Audience :: Developers
Classifier: Intended Audience :: System Administrators
Classifier: License :: OSI Approved :: Apache Software License
